joplin_parse/__init__.py
joplin_parse/main.py
joplin_parse/utils.py
joplin_parse-0.1.1.dist-info/WHEEL
joplin_parse-0.1.1.dist-info/METADATA
joplin_parse-0.1.1.dist-info/RECORD
