Metadata-Version: 2.1
Name: joplin-parse
Version: 0.1.1
Summary: Turn Joplin database into public wiki
Author: Rasul Kireev
Author-email: me@rasulkireev.com
Requires-Python: >=3.7,<4.0
Classifier: Programming Language :: Python :: 3
Classifier: Programming Language :: Python :: 3.7
Classifier: Programming Language :: Python :: 3.8
Requires-Dist: asyncio (>=3.4.3,<4.0.0)
Requires-Dist: joplin-api (>=1.5.6,<2.0.0)
Requires-Dist: wrapt (>=1.12.1,<2.0.0)
